nicepyright/__init__.py
nicepyright/definitions.py
nicepyright/main.py
nicepyright/messages.py
nicepyright/py.typed
nicepyright/utils.py
nicepyright-0.1.2.dist-info/entry_points.txt
nicepyright-0.1.2.dist-info/WHEEL
nicepyright-0.1.2.dist-info/METADATA
nicepyright-0.1.2.dist-info/RECORD
