Metadata-Version: 2.1
Name: nicepyright
Version: 0.1.2
Summary: 
Author: Pedro Batista
Author-email: pedrovhb@gmail.com
Requires-Python: >=3.8,<4.0
Classifier: Programming Language :: Python :: 3
Classifier: Programming Language :: Python :: 3.8
Classifier: Programming Language :: Python :: 3.9
Classifier: Programming Language :: Python :: 3.10
Classifier: Programming Language :: Python :: 3.11
Requires-Dist: parse (>=1.19.0,<2.0.0)
Requires-Dist: pyright (>=1.1.288,<2.0.0)
Requires-Dist: rich (>=13.0.1,<14.0.0)
